{
    "minecraft_version": "1.8",
    "packagename": "net.minecraft.client.gui",
    "classname": "FontRenderer",
    "obfuscated_classname": "bty",
    "methods": [
        {
            "method_name": "renderUnicodeChar",
            "obfuscated_name": "func_78277_a",
            "type": {
                "parameters_type": [
                    "char", "boolean"
                ],
                "return_type": "float",
            }
        }
    ],
    "fields": [
        {
            "field_name": "locationFontTexture",
            "obfuscated_name: "field_111273_g"
        },
        {
            "field_name": "renderEngine",
            "obfuscated_name: "field_78298_i"
        },
        {
            "field_name": "unicodeFlag",
            "obfuscated_name: "field_78293_l"
        },
        {
            "field_name": "unicodePageLocations",
            "obfuscated_name: "field_111274_c"
        },
        {
            "field_name": "posX",
            "obfuscated_name: "field_78295_j"
        },
        {
            "field_name": "posY",
            "obfuscated_name: "field_78296_k"
        },
        {
            "field_name": "FONT_HEIGHT",
            "obfuscated_name: "field_78288_b"
        },
        {
            "field_name": "glyphWidth",
            "obfuscated_name: "field_78287_e"
        }
    ]
}